nlpcmd_ai/__init__.py
nlpcmd_ai/base_handler.py
nlpcmd_ai/cli.py
nlpcmd_ai/config.py
nlpcmd_ai/engine.py
nlpcmd_ai/handlers.py
nlpcmd_ai/platform_utils.py
nlpcmd_ai-0.1.3.dist-info/licenses/LICENSE
nlpcmd_ai-0.1.3.dist-info/METADATA
nlpcmd_ai-0.1.3.dist-info/WHEEL
nlpcmd_ai-0.1.3.dist-info/entry_points.txt
nlpcmd_ai-0.1.3.dist-info/top_level.txt
nlpcmd_ai-0.1.3.dist-info/RECORD
