Metadata-Version: 2.4
Name: nlpcmd-ai
Version: 0.1.3
Summary: AI-powered CLI assistant that understands natural language - transform plain English into system commands on Windows, Linux, and macOS
Author-email: Avik <avikgreat@gmail.com>
Maintainer-email: Avik <avikgreat@gmail.com>
License: MIT
Project-URL: Homepage, https://github.com/Avikg/nlp_terminal_cmd
Project-URL: Documentation, https://github.com/Avikg/nlp_terminal_cmd#readme
Project-URL: Repository, https://github.com/Avikg/nlp_terminal_cmd
Project-URL: Bug Tracker, https://github.com/Avikg/nlp_terminal_cmd/issues
Project-URL: Issues, https://github.com/Avikg/nlp_terminal_cmd/issues
Project-URL: Changelog, https://github.com/Avikg/nlp_terminal_cmd/releases
Project-URL: Source Code, https://github.com/Avikg/nlp_terminal_cmd
Project-URL: Download, https://pypi.org/project/nlpcmd-ai/
Keywords: cli,nlp,ai,command-line,assistant,natural-language,chatgpt,llm,cross-platform,terminal,shell,automation,openai,anthropic,ollama,gpt-4,claude
Classifier: Development Status :: 4 - Beta
Classifier: Intended Audience :: Developers
Classifier: Intended Audience :: System Administrators
Classifier: Intended Audience :: End Users/Desktop
Classifier: License :: OSI Approved :: MIT License
Classifier: Operating System :: OS Independent
Classifier: Operating System :: Microsoft :: Windows
Classifier: Operating System :: Microsoft :: Windows :: Windows 10
Classifier: Operating System :: Microsoft :: Windows :: Windows 11
Classifier: Operating System :: POSIX :: Linux
Classifier: Operating System :: MacOS
Classifier: Programming Language :: Python :: 3
Classifier: Programming Language :: Python :: 3.8
Classifier: Programming Language :: Python :: 3.9
Classifier: Programming Language :: Python :: 3.10
Classifier: Programming Language :: Python :: 3.11
Classifier: Programming Language :: Python :: 3.12
Classifier: Programming Language :: Python :: 3.13
Classifier: Topic :: Software Development :: Libraries :: Python Modules
Classifier: Topic :: System :: Shells
Classifier: Topic :: System :: System Shells
Classifier: Topic :: System :: Systems Administration
Classifier: Topic :: Utilities
Classifier: Topic :: Scientific/Engineering :: Artificial Intelligence
Classifier: Environment :: Console
Classifier: Natural Language :: English
Requires-Python: >=3.8
License-File: LICENSE
Requires-Dist: openai>=1.0.0
Requires-Dist: anthropic>=0.18.0
Requires-Dist: python-dotenv>=1.0.0
Requires-Dist: rich>=13.0.0
Requires-Dist: click>=8.1.0
Requires-Dist: pydantic>=2.0.0
Requires-Dist: requests>=2.31.0
Requires-Dist: pyyaml>=6.0.0
Requires-Dist: psutil>=5.9.0
Provides-Extra: dev
Requires-Dist: pytest>=7.0.0; extra == "dev"
Requires-Dist: pytest-cov>=4.0.0; extra == "dev"
Requires-Dist: black>=23.0.0; extra == "dev"
Requires-Dist: ruff>=0.1.0; extra == "dev"
Requires-Dist: mypy>=1.0.0; extra == "dev"
Requires-Dist: build>=0.10.0; extra == "dev"
Requires-Dist: twine>=4.0.0; extra == "dev"
Provides-Extra: local
Requires-Dist: ollama>=0.1.0; extra == "local"
Provides-Extra: all
Requires-Dist: pytest>=7.0.0; extra == "all"
Requires-Dist: pytest-cov>=4.0.0; extra == "all"
Requires-Dist: black>=23.0.0; extra == "all"
Requires-Dist: ruff>=0.1.0; extra == "all"
Requires-Dist: mypy>=1.0.0; extra == "all"
Requires-Dist: build>=0.10.0; extra == "all"
Requires-Dist: twine>=4.0.0; extra == "all"
Requires-Dist: ollama>=0.1.0; extra == "all"
Dynamic: license-file
